MANIFEST.in
README.txt
setup.py
src/requires.txt
src/m3_autologin/__init__.py
src/m3_autologin/api.py
src/m3_autologin/app_meta.py
src/m3_autologin/models.py
src/m3_autologin/version.py
src/m3_autologin/views.py
src/m3_autologin.egg-info/PKG-INFO
src/m3_autologin.egg-info/SOURCES.txt
src/m3_autologin.egg-info/dependency_links.txt
src/m3_autologin.egg-info/top_level.txt
src/m3_autologin/migrations/0001_initial.py
src/m3_autologin/migrations/0002_tickets.py
src/m3_autologin/migrations/__init__.py
src/tests/__init__.py
src/tests/manage.py
src/tests/prepare_env.py
src/tests/settings.py
src/tests/shell.sh
src/tests/test.sh
src/tests/urls.py
src/tests/version.py
src/tests/core/__init__.py
src/tests/core/tests.py